mctorch/__init__.py
mctorch/mctorch.py
mctorch/util.py
mctorch-0.1.0.dist-info/AUTHORS.rst
mctorch-0.1.0.dist-info/LICENSE
mctorch-0.1.0.dist-info/METADATA
mctorch-0.1.0.dist-info/WHEEL
mctorch-0.1.0.dist-info/top_level.txt
mctorch-0.1.0.dist-info/RECORD
